specify_cli/__init__.py
specify_cli/acceptance.py
specify_cli/doc_generators.py
specify_cli/doc_state.py
specify_cli/frontmatter.py
specify_cli/gap_analysis.py
specify_cli/gitignore_manager.py
specify_cli/guards.py
specify_cli/legacy_detector.py
specify_cli/manifest.py
specify_cli/mission.py
specify_cli/plan_validation.py
specify_cli/task_metadata_validation.py
specify_cli/tasks_support.py
specify_cli/text_sanitization.py
specify_cli/verify_enhanced.py
specify_cli/version_utils.py
specify_cli/workspace_context.py
specify_cli/agent_utils/README.md
specify_cli/agent_utils/__init__.py
specify_cli/agent_utils/status.py
specify_cli/cli/__init__.py
specify_cli/cli/helpers.py
specify_cli/cli/step_tracker.py
specify_cli/cli/ui.py
specify_cli/cli/commands/__init__.py
specify_cli/cli/commands/accept.py
specify_cli/cli/commands/context.py
specify_cli/cli/commands/dashboard.py
specify_cli/cli/commands/implement.py
specify_cli/cli/commands/init.py
specify_cli/cli/commands/init_help.py
specify_cli/cli/commands/merge.py
specify_cli/cli/commands/mission.py
specify_cli/cli/commands/ops.py
specify_cli/cli/commands/orchestrate.py
specify_cli/cli/commands/repair.py
specify_cli/cli/commands/research.py
specify_cli/cli/commands/sync.py
specify_cli/cli/commands/upgrade.py
specify_cli/cli/commands/validate_encoding.py
specify_cli/cli/commands/validate_tasks.py
specify_cli/cli/commands/verify.py
specify_cli/cli/commands/agent/README.md
specify_cli/cli/commands/agent/__init__.py
specify_cli/cli/commands/agent/config.py
specify_cli/cli/commands/agent/context.py
specify_cli/cli/commands/agent/feature.py
specify_cli/cli/commands/agent/release.py
specify_cli/cli/commands/agent/tasks.py
specify_cli/cli/commands/agent/workflow.py
specify_cli/core/__init__.py
specify_cli/core/agent_context.py
specify_cli/core/config.py
specify_cli/core/context_validation.py
specify_cli/core/dependency_graph.py
specify_cli/core/dependency_resolver.py
specify_cli/core/feature_detection.py
specify_cli/core/git_ops.py
spec_kitty_cli-0.13.20.dist-info/METADATA
spec_kitty_cli-0.13.20.dist-info/WHEEL
spec_kitty_cli-0.13.20.dist-info/entry_points.txt
spec_kitty_cli-0.13.20.dist-info/licenses/LICENSE
spec_kitty_cli-0.13.20.dist-info/RECORD
