Metadata-Version: 2.4
Name: spec-kitty-cli
Version: 0.13.20
Summary: Spec Kitty, a tool for Specification Driven Development (SDD) agentic projects, with kanban and git worktree isolation.
Project-URL: Repository, https://github.com/Priivacy-ai/spec-kitty
Project-URL: Issues, https://github.com/Priivacy-ai/spec-kitty/issues
Project-URL: Documentation, https://priivacy-ai.github.io/spec-kitty/
Project-URL: Changelog, https://github.com/Priivacy-ai/spec-kitty/blob/main/CHANGELOG.md
Author: Spec Kitty Contributors
Maintainer: Spec Kitty Contributors
License: MIT License
License-File: LICENSE
Keywords: agentic-development,ai-agents,ai-coding,claude-code,cli,code-generation,feature-specs,git-worktree,kanban,llm-tools,planning,requirements,sdd,spec-driven-development,specification,workflow-automation
Classifier: Development Status :: 4 - Beta
Classifier: Environment :: Console
Classifier: Intended Audience :: Developers
Classifier: License :: OSI Approved :: MIT License
Classifier: Operating System :: OS Independent
Classifier: Programming Language :: Python :: 3
Classifier: Programming Language :: Python :: 3.11
Classifier: Programming Language :: Python :: 3.12
Classifier: Programming Language :: Python :: 3.13
Classifier: Topic :: Software Development
Classifier: Topic :: Software Development :: Code Generators
Classifier: Topic :: Software Development :: Documentation
Classifier: Topic :: Software Development :: Quality Assurance
Classifier: Topic :: Software Development :: Version Control
Classifier: Topic :: Software Development :: Version Control :: Git
Classifier: Topic :: Utilities
Classifier: Typing :: Typed
Requires-Python: >=3.11
Requires-Dist: httpx[socks]
Requires-Dist: packaging>=23.0
Requires-Dist: platformdirs
Requires-Dist: psutil>=5.9.0
Requires-Dist: pydantic>=2.0
Requires-Dist: python-ulid>=1.1.0
Requires-Dist: pyyaml>=6.0
Requires-Dist: readchar
Requires-Dist: rich
Requires-Dist: ruamel-yaml>=0.18.0
Requires-Dist: truststore>=0.10.4
Requires-Dist: typer
Provides-Extra: test
Requires-Dist: build>=1.0.0; extra == 'test'
Requires-Dist: pytest>=7.4; extra == 'test'
